[
  {"TIMEID": 1, "EMPID": "E001", "PROJECTID": "P001", "START_TIME": "2025-04-19 20:58:08", "STOP_TIME": "2025-04-19 21:58:08", "NOTES": "Worked on initial setup", "MANUAL_ENTRY": 1, "TOTAL_MINUTES": 60},
  {"TIMEID": 2, "EMPID": "E001", "PROJECTID": "P001", "START_TIME": "2025-04-20 09:30:00", "STOP_TIME": "2025-04-20 11:00:00", "NOTES": "Entered start/stop manually", "MANUAL_ENTRY": 1, "TOTAL_MINUTES": 90},
  {"TIMEID": 3, "EMPID": "TEST01", "PROJECTID": "P001", "START_TIME": "2025-04-21 10:00:00", "STOP_TIME": "2025-04-21 11:30:00", "NOTES": "Manual entry for testing", "MANUAL_ENTRY": 1, "TOTAL_MINUTES": 90},
  {"TIMEID": 4, "EMPID": "E001", "PROJECTID": "P002", "START_TIME": "2025-04-22 13:00:00", "STOP_TIME": "2025-04-22 14:00:00", "NOTES": "Casey: project planning", "MANUAL_ENTRY": 1, "TOTAL_MINUTES": 60},
  {"TIMEID": 5, "EMPID": "TEST01", "PROJECTID": "P002", "START_TIME": "2025-04-22 15:00:00", "STOP_TIME": "2025-04-22 16:00:00", "NOTES": "Tess: wireframing", "MANUAL_ENTRY": 1, "TOTAL_MINUTES": 60},
  {"TIMEID": 6, "EMPID": "E0009", "PROJECTID": "P003", "START_TIME": "2025-04-23 09:00:00", "STOP_TIME": "2025-04-23 10:30:00", "NOTES": "Liesl: team check-ins and documentation", "MANUAL_ENTRY": 1, "TOTAL_MINUTES": 90},
  {"TIMEID": 7, "EMPID": "E004", "PROJECTID": "P003", "START_TIME": "2025-04-23 11:00:00", "STOP_TIME": "2025-04-23 12:00:00", "NOTES": "Erika: stakeholder meeting", "MANUAL_ENTRY": 1, "TOTAL_MINUTES": 60},
  {"TIMEID": 8, "EMPID": "E0009", "PROJECTID": "P001", "START_TIME": "2025-04-24 04:52:06", "STOP_TIME": "2025-04-24 05:52:06", "NOTES": "Liesl: debugging session", "MANUAL_ENTRY": 1, "TOTAL_MINUTES": 60},
  {"TIMEID": 9, "EMPID": "TEST01", "PROJECTID": "P001", "START_TIME": "2025-04-24 03:52:06", "STOP_TIME": "2025-04-24 04:52:06", "NOTES": "Tess: finished documentation", "MANUAL_ENTRY": 1, "TOTAL_MINUTES": 60},
  {"TIMEID": 10, "EMPID": "E003", "PROJECTID": "P001", "START_TIME": "2025-04-23 09:00:00", "STOP_TIME": "2025-04-23 10:30:00", "NOTES": "Yesac: planning meeting", "MANUAL_ENTRY": 1, "TOTAL_MINUTES": 90},
  {"TIMEID": 11, "EMPID": "E003", "PROJECTID": "P002", "START_TIME": "2025-04-24 13:00:00", "STOP_TIME": "2025-04-24 14:15:00", "NOTES": "Yesac: reviewed reports", "MANUAL_ENTRY": 1, "TOTAL_MINUTES": 75},
  {"TIMEID": 12, "EMPID": "E011", "PROJECTID": "P001", "START_TIME": "2025-04-24 09:00:00", "STOP_TIME": "2025-04-24 10:00:00", "NOTES": "Nina: daily task", "MANUAL_ENTRY": 1, "TOTAL_MINUTES": 60},
  {"TIMEID": 13, "EMPID": "E012", "PROJECTID": "P002", "START_TIME": "2025-04-24 10:00:00", "STOP_TIME": "2025-04-24 11:00:00", "NOTES": "Tom: daily task", "MANUAL_ENTRY": 1, "TOTAL_MINUTES": 60},
  {"TIMEID": 14, "EMPID": "E013", "PROJECTID": "P003", "START_TIME": "2025-04-24 11:00:00", "STOP_TIME": "2025-04-24 12:00:00", "NOTES": "Sara: daily task", "MANUAL_ENTRY": 1, "TOTAL_MINUTES": 60},
  {"TIMEID": 15, "EMPID": "E014", "PROJECTID": "P004", "START_TIME": "2025-04-24 12:00:00", "STOP_TIME": "2025-04-24 13:00:00", "NOTES": "Alex: daily task", "MANUAL_ENTRY": 1, "TOTAL_MINUTES": 60},
  {"TIMEID": 16, "EMPID": "E015", "PROJECTID": "P001", "START_TIME": "2025-04-24 13:00:00", "STOP_TIME": "2025-04-24 14:00:00", "NOTES": "Jamie: daily task", "MANUAL_ENTRY": 1, "TOTAL_MINUTES": 60},
  {"TIMEID": 17, "EMPID": "E016", "PROJECTID": "P002", "START_TIME": "2025-04-24 14:00:00", "STOP_TIME": "2025-04-24 15:00:00", "NOTES": "Taylor: daily task", "MANUAL_ENTRY": 1, "TOTAL_MINUTES": 60},
  {"TIMEID": 18, "EMPID": "E9001", "PROJECTID": "P10001", "START_TIME": "2024-04-05 09:50:00", "STOP_TIME": "2024-04-05 11:59:00", "NOTES": "Integer ac", "MANUAL_ENTRY": 0, "TOTAL_MINUTES": 129},
  {"TIMEID": 19, "EMPID": "E9003", "PROJECTID": "P10003", "START_TIME": "2024-12-09 16:47:00", "STOP_TIME": "2024-12-09 18:01:00", "NOTES": "Vestibulum", "MANUAL_ENTRY": 1, "TOTAL_MINUTES": 74},
  {"TIMEID": 20, "EMPID": "E9005", "PROJECTID": "P10005", "START_TIME": "2024-04-14 04:01:00", "STOP_TIME": "2024-04-14 05:17:00", "NOTES": "Suspendisse", "MANUAL_ENTRY": 1, "TOTAL_MINUTES": 76},
  {"TIMEID": 21, "EMPID": "E9006", "PROJECTID": "P10006", "START_TIME": "2025-01-08 20:09:00", "STOP_TIME": "2025-01-08 21:05:00", "NOTES": "Mauris enim", "MANUAL_ENTRY": 0, "TOTAL_MINUTES": 56},
  {"TIMEID": 22, "EMPID": "E9005", "PROJECTID": "P10005", "START_TIME": "2025-03-11 09:51:00", "STOP_TIME": "2025-03-11 11:03:00", "NOTES": "Sed sagittis", "MANUAL_ENTRY": 1, "TOTAL_MINUTES": 72},
  {"TIMEID": 23, "EMPID": "E9006", "PROJECTID": "P10006", "START_TIME": "2025-01-24 03:11:00", "STOP_TIME": "2025-01-24 04:21:00", "NOTES": "Cras non tortor", "MANUAL_ENTRY": 0, "TOTAL_MINUTES": 70},
  {"TIMEID": 24, "EMPID": "E9006", "PROJECTID": "P10006", "START_TIME": "2024-05-29 07:58:00", "STOP_TIME": "2024-05-29 09:56:00", "NOTES": "Donec diam", "MANUAL_ENTRY": 1, "TOTAL_MINUTES": 118},
  {"TIMEID": 25, "EMPID": "E9006", "PROJECTID": "P10006", "START_TIME": "2025-01-16 14:46:00", "STOP_TIME": "2025-01-16 15:41:00", "NOTES": "Phasellus in", "MANUAL_ENTRY": 0, "TOTAL_MINUTES": 55},
  {"TIMEID": 26, "EMPID": "E9007", "PROJECTID": "P10007", "START_TIME": "2024-06-23 21:55:00", "STOP_TIME": "2024-06-23 22:51:00", "NOTES": "Duis bibendum", "MANUAL_ENTRY": 0, "TOTAL_MINUTES": 56},
  {"TIMEID": 27, "EMPID": "E9007", "PROJECTID": "P10009", "START_TIME": "2024-03-10 19:27:00", "STOP_TIME": "2024-03-10 20:39:00", "NOTES": "Sed sagittis", "MANUAL_ENTRY": 1, "TOTAL_MINUTES": 72},
  {"TIMEID": 28, "EMPID": "E9007", "PROJECTID": "P10009", "START_TIME": "2024-06-22 06:15:00", "STOP_TIME": "2024-06-22 09:11:00", "NOTES": "In sagittis", "MANUAL_ENTRY": 1, "TOTAL_MINUTES": 176},
  {"TIMEID": 29, "EMPID": "E9011", "PROJECTID": "P10010", "START_TIME": "2025-01-23 01:01:00", "STOP_TIME": "2025-01-23 02:03:00", "NOTES": "Duis aliquam", "MANUAL_ENTRY": 1, "TOTAL_MINUTES": 62},
  {"TIMEID": 30, "EMPID": "E9011", "PROJECTID": "P10011", "START_TIME": "2025-02-13 04:19:00", "STOP_TIME": "2025-02-13 05:57:00", "NOTES": "In congue", "MANUAL_ENTRY": 1, "TOTAL_MINUTES": 98},
  {"TIMEID": 31, "EMPID": "E9012", "PROJECTID": "P10012", "START_TIME": "2024-06-15 19:12:00", "STOP_TIME": "2024-06-15 20:44:00", "NOTES": "Maecenas ut", "MANUAL_ENTRY": 0, "TOTAL_MINUTES": 92},
  {"TIMEID": 32, "EMPID": "E9014", "PROJECTID": "P10014", "START_TIME": "2025-04-05 09:30:00", "STOP_TIME": "2025-04-06 11:09:00", "NOTES": "Pellentesque", "MANUAL_ENTRY": 1, "TOTAL_MINUTES": 1539},
  {"TIMEID": 33, "EMPID": "E9015", "PROJECTID": "P10015", "START_TIME": "2024-08-07 08:32:00", "STOP_TIME": "2024-08-07 19:50:00", "NOTES": "Nulla ute", "MANUAL_ENTRY": 1, "TOTAL_MINUTES": 678},
  {"TIMEID": 34, "EMPID": "E9016", "PROJECTID": "P10016", "START_TIME": "2025-02-04 08:28:00", "STOP_TIME": "2025-02-04 10:34:00", "NOTES": "Praesent id", "MANUAL_ENTRY": 0, "TOTAL_MINUTES": 126},
  {"TIMEID": 35, "EMPID": "E9017", "PROJECTID": "P10017", "START_TIME": "2025-03-31 13:09:00", "STOP_TIME": "2025-03-31 14:09:00", "NOTES": "Quisque posuere", "MANUAL_ENTRY": 1, "TOTAL_MINUTES": 60},
  {"TIMEID": 36, "EMPID": "E9018", "PROJECTID": "P10018", "START_TIME": "2025-02-05 02:50:00", "STOP_TIME": "2025-02-05 05:12:00", "NOTES": "Vestibulum", "MANUAL_ENTRY": 0, "TOTAL_MINUTES": 142},
  {"TIMEID": 37, "EMPID": "E9019", "PROJECTID": "P10020", "START_TIME": "2024-10-09 13:38:00", "STOP_TIME": "2024-10-09 15:09:00", "NOTES": "Fusce posuere", "MANUAL_ENTRY": 1, "TOTAL_MINUTES": 91},
  {"TIMEID": 38, "EMPID": "E9021", "PROJECTID": "P10021", "START_TIME": "2024-03-26 03:58:00", "STOP_TIME": "2024-03-26 06:12:00", "NOTES": "In quis justo", "MANUAL_ENTRY": 1, "TOTAL_MINUTES": 134},
  {"TIMEID": 39, "EMPID": "E9024", "PROJECTID": "P10024", "START_TIME": "2024-10-30 11:00:00", "STOP_TIME": "2024-10-30 11:45:00", "NOTES": "Maecenas ut", "MANUAL_ENTRY": 0, "TOTAL_MINUTES": 45},
  {"TIMEID": 40, "EMPID": "E9025", "PROJECTID": "P10025", "START_TIME": "2025-04-07 03:24:00", "STOP_TIME": "2025-04-07 05:22:00", "NOTES": "Donec diam", "MANUAL_ENTRY": 0, "TOTAL_MINUTES": 118}
]